LICENSE.txt
MANIFEST.in
README.md
dependency_links.txt
requirements.txt
setup.cfg
setup.py
infertweet/__init__.py
infertweet/config.py
infertweet/country.py
infertweet/twitter.py
infertweet.egg-info/PKG-INFO
infertweet.egg-info/SOURCES.txt
infertweet.egg-info/dependency_links.txt
infertweet.egg-info/requires.txt
infertweet.egg-info/top_level.txt
infertweet/corpus/__init__.py
infertweet/corpus/artfestival.py
infertweet/corpus/semeval.py
infertweet/corpus/stanford.py
infertweet/corpus/twitter_corpus.py
infertweet/corpus/twittercorpus.py
infertweet/sentiment/__init__.py
infertweet/sentiment/experiment.py
infertweet/sentiment/old_classify.py
infertweet/sentiment/plot.py
infertweet/sentiment/rpcserver.py
infertweet/sentiment/tokenizer.py
infertweet/sentiment/train.py
infertweet/tests/__init__.py
infertweet/tests/config_test.py
infertweet/tests/country_test.py
infertweet/tests/semeval_test.py
infertweet/tests/twitter_test.py
infertweet/web/__init__.py
infertweet/web/main.py
infertweet/web/static/favicon.ico
infertweet/web/static/robots.txt
infertweet/web/static/style.css
infertweet/web/templates/active-thanks.html
infertweet/web/templates/active.html
infertweet/web/templates/base.html
infertweet/web/templates/index.html
infertweet/web/templates/misclassified.html
infertweet/web/templates/sentiment.html