Metadata-Version: 1.1
Name: infertweet
Version: 0.2
Summary: Infer information from Tweets. Useful for human-centered computing tasks, such as sentiment analysis, location prediction, authorship profiling and more!
Home-page: http://www.github.com/bwbaugh/infertweet
Author: Wesley Baugh
Author-email: wesley@bwbaugh.com
License: Creative Commons Attribution-NonCommercial-ShareAlike 3.0 Unported License
Platform: UNKNOWN
Classifier: Intended Audience :: Developers
Classifier: Intended Audience :: Science/Research
Classifier: Natural Language :: English
Classifier: Programming Language :: Python
Classifier: Programming Language :: Python :: 2.7
Classifier: Programming Language :: Python :: Implementation :: PyPy
Classifier: Topic :: Scientific/Engineering :: Artificial Intelligence
Classifier: Topic :: Scientific/Engineering :: Information Analysis
Classifier: Topic :: Software Development :: Libraries :: Python Modules
Classifier: Topic :: Text Processing :: Linguistic
